odoo10_addon_account_move_line_report_xls-10.0.1.0.0.99.dev4-py2.7-nspkg.pth
odoo/addons/account_move_line_report_xls/README.rst
odoo/addons/account_move_line_report_xls/__init__.py
odoo/addons/account_move_line_report_xls/__manifest__.py
odoo/addons/account_move_line_report_xls/i18n/account_move_line_report_xls.pot
odoo/addons/account_move_line_report_xls/i18n/fi.po
odoo/addons/account_move_line_report_xls/i18n/fr.po
odoo/addons/account_move_line_report_xls/i18n/nl.po
odoo/addons/account_move_line_report_xls/models/__init__.py
odoo/addons/account_move_line_report_xls/models/account_move_line.py
odoo/addons/account_move_line_report_xls/report/__init__.py
odoo/addons/account_move_line_report_xls/report/move_line_list_xls.py
odoo/addons/account_move_line_report_xls/report/move_line_list_xls.xml
odoo/addons/account_move_line_report_xls/static/description/icon.png
odoo/addons/account_move_line_report_xls/static/description/icon.svg
odoo/addons/account_move_line_report_xls/static/description/index.html
odoo/addons/account_move_line_report_xls/static/description/journal_items.png
odoo/addons/account_move_line_report_xls/static/description/oca_logo.png
odoo/addons/account_move_line_report_xls/tests/__init__.py
odoo/addons/account_move_line_report_xls/tests/test_aml_report_xlsx.py
odoo10_addon_account_move_line_report_xls-10.0.1.0.0.99.dev4.dist-info/METADATA
odoo10_addon_account_move_line_report_xls-10.0.1.0.0.99.dev4.dist-info/RECORD
odoo10_addon_account_move_line_report_xls-10.0.1.0.0.99.dev4.dist-info/WHEEL
odoo10_addon_account_move_line_report_xls-10.0.1.0.0.99.dev4.dist-info/namespace_packages.txt
odoo10_addon_account_move_line_report_xls-10.0.1.0.0.99.dev4.dist-info/top_level.txt
